prioritymap/__init__.py
prioritymap/prioritymap.py
prioritymap-0.0.2.dist-info/LICENSE.txt
prioritymap-0.0.2.dist-info/METADATA
prioritymap-0.0.2.dist-info/WHEEL
prioritymap-0.0.2.dist-info/top_level.txt
prioritymap-0.0.2.dist-info/RECORD
